featexp/__init__.py
featexp/base.py
featexp-0.0.7.dist-info/AUTHORS.rst
featexp-0.0.7.dist-info/LICENSE
featexp-0.0.7.dist-info/METADATA
featexp-0.0.7.dist-info/WHEEL
featexp-0.0.7.dist-info/top_level.txt
featexp-0.0.7.dist-info/RECORD
