Metadata-Version: 2.1
Name: featexp
Version: 0.0.7
Summary: Feature exploration for supervised learning
Home-page: https://github.com/abhayspawar/featexp
Author: Abhay Pawar
Author-email: abhayspawar@gmail.com
License: UNKNOWN
Platform: UNKNOWN
Classifier: Programming Language :: Python :: 3
Classifier: Programming Language :: Python :: 2
Classifier: License :: OSI Approved :: MIT License
Classifier: Operating System :: OS Independent
Requires-Dist: pandas
Requires-Dist: numpy
Requires-Dist: matplotlib
